README.rst
setup.py
html5charref/__init__.py
html5charref.egg-info/PKG-INFO
html5charref.egg-info/SOURCES.txt
html5charref.egg-info/dependency_links.txt
html5charref.egg-info/requires.txt
html5charref.egg-info/top_level.txt